<?xml version="1.0" standalone="yes"?>
<NewDataSet>
  <xs:schema id="NewDataSet" xmlns="" xmlns:xs="http://www.w3.org/2001/XMLSchema" xmlns:msdata="urn:schemas-microsoft-com:xml-msdata">
    <xs:element name="NewDataSet" msdata:IsDataSet="true" msdata:UseCurrentLocale="true">
      <xs:complexType>
        <xs:choice minOccurs="0" maxOccurs="unbounded">
          <xs:element name="Prezzi">
            <xs:complexType>
              <xs:sequence>
                <xs:element name="Data" type="xs:string" minOccurs="0" />
                <xs:element name="Mercato" type="xs:string" minOccurs="0" />
                <xs:element name="Ora" type="xs:string" minOccurs="0" />
                <xs:element name="PUN" type="xs:string" minOccurs="0" />
                <xs:element name="NAT" type="xs:string" minOccurs="0" />
                <xs:element name="CNOR" type="xs:string" minOccurs="0" />
                <xs:element name="CSUD" type="xs:string" minOccurs="0" />
                <xs:element name="NORD" type="xs:string" minOccurs="0" />
                <xs:element name="SARD" type="xs:string" minOccurs="0" />
                <xs:element name="SICI" type="xs:string" minOccurs="0" />
                <xs:element name="SUD" type="xs:string" minOccurs="0" />
                <xs:element name="AUST" type="xs:string" minOccurs="0" />
                <xs:element name="BRNN" type="xs:string" minOccurs="0" />
                <xs:element name="COAC" type="xs:string" minOccurs="0" />
                <xs:element name="CORS" type="xs:string" minOccurs="0" />
                <xs:element name="FOGN" type="xs:string" minOccurs="0" />
                <xs:element name="FRAN" type="xs:string" minOccurs="0" />
                <xs:element name="GREC" type="xs:string" minOccurs="0" />
                <xs:element name="MFTV" type="xs:string" minOccurs="0" />
                <xs:element name="PRGP" type="xs:string" minOccurs="0" />
                <xs:element name="ROSN" type="xs:string" minOccurs="0" />
                <xs:element name="SLOV" type="xs:string" minOccurs="0" />
                <xs:element name="SVIZ" type="xs:string" minOccurs="0" />
                <xs:element name="BSP" type="xs:string" minOccurs="0" />
                <xs:element name="MALT" type="xs:string" minOccurs="0" />
                <xs:element name="XAUS" type="xs:string" minOccurs="0" />
                <xs:element name="XFRA" type="xs:string" minOccurs="0" />
              </xs:sequence>
            </xs:complexType>
          </xs:element>
        </xs:choice>
      </xs:complexType>
    </xs:element>
  </xs:schema>
  <Prezzi>
    <Data>20181217</Data>
    <Mercato>MGP</Mercato>
    <Ora>1</Ora>
    <PUN>55,500000</PUN>
    <NAT>55,500000</NAT>
    <CNOR>55,500000</CNOR>
    <CSUD>55,500000</CSUD>
    <NORD>55,500000</NORD>
    <SARD>55,500000</SARD>
    <SICI>55,500000</SICI>
    <SUD>55,500000</SUD>
    <AUST>55,500000</AUST>
    <BRNN>55,500000</BRNN>
    <COAC>55,500000</COAC>
    <CORS>55,500000</CORS>
    <FOGN>55,500000</FOGN>
    <FRAN>55,500000</FRAN>
    <GREC>55,500000</GREC>
    <MFTV>55,500000</MFTV>
    <PRGP>55,500000</PRGP>
    <ROSN>55,500000</ROSN>
    <SLOV>55,500000</SLOV>
    <SVIZ>55,500000</SVIZ>
    <BSP>55,500000</BSP>
    <MALT>55,500000</MALT>
    <XAUS>55,500000</XAUS>
    <XFRA>55,500000</XFRA>
  </Prezzi>
  <Prezzi>
    <Data>20181217</Data>
    <Mercato>MGP</Mercato>
    <Ora>2</Ora>
    <PUN>54,330000</PUN>
    <NAT>54,330000</NAT>
    <CNOR>54,330000</CNOR>
    <CSUD>54,330000</CSUD>
    <NORD>54,330000</NORD>
    <SARD>54,330000</SARD>
    <SICI>54,330000</SICI>
    <SUD>54,330000</SUD>
    <AUST>54,330000</AUST>
    <BRNN>54,330000</BRNN>
    <COAC>54,330000</COAC>
    <CORS>54,330000</CORS>
    <FOGN>54,330000</FOGN>
    <FRAN>54,330000</FRAN>
    <GREC>54,330000</GREC>
    <MFTV>54,330000</MFTV>
    <PRGP>54,330000</PRGP>
    <ROSN>54,330000</ROSN>
    <SLOV>54,330000</SLOV>
    <SVIZ>54,330000</SVIZ>
    <BSP>54,330000</BSP>
    <MALT>54,330000</MALT>
    <XAUS>54,330000</XAUS>
    <XFRA>54,330000</XFRA>
  </Prezzi>
  <Prezzi>
    <Data>20181217</Data>
    <Mercato>MGP</Mercato>
    <Ora>3</Ora>
    <PUN>54,230000</PUN>
    <NAT>54,230000</NAT>
    <CNOR>54,230000</CNOR>
    <CSUD>54,230000</CSUD>
    <NORD>54,230000</NORD>
    <SARD>54,230000</SARD>
    <SICI>54,230000</SICI>
    <SUD>54,230000</SUD>
    <AUST>54,230000</AUST>
    <BRNN>54,230000</BRNN>
    <COAC>54,230000</COAC>
    <CORS>54,230000</CORS>
    <FOGN>54,230000</FOGN>
    <FRAN>54,230000</FRAN>
    <GREC>54,230000</GREC>
    <MFTV>54,230000</MFTV>
    <PRGP>54,230000</PRGP>
    <ROSN>54,230000</ROSN>
    <SLOV>54,230000</SLOV>
    <SVIZ>54,230000</SVIZ>
    <BSP>54,230000</BSP>
    <MALT>54,230000</MALT>
    <XAUS>54,230000</XAUS>
    <XFRA>54,230000</XFRA>
  </Prezzi>
  <Prezzi>
    <Data>20181217</Data>
    <Mercato>MGP</Mercato>
    <Ora>4</Ora>
    <PUN>53,830000</PUN>
    <NAT>53,830000</NAT>
    <CNOR>53,830000</CNOR>
    <CSUD>53,830000</CSUD>
    <NORD>53,830000</NORD>
    <SARD>53,830000</SARD>
    <SICI>53,830000</SICI>
    <SUD>53,830000</SUD>
    <AUST>53,830000</AUST>
    <BRNN>53,830000</BRNN>
    <COAC>53,830000</COAC>
    <CORS>53,830000</CORS>
    <FOGN>53,830000</FOGN>
    <FRAN>53,830000</FRAN>
    <GREC>53,830000</GREC>
    <MFTV>53,830000</MFTV>
    <PRGP>53,830000</PRGP>
    <ROSN>53,830000</ROSN>
    <SLOV>53,830000</SLOV>
    <SVIZ>53,830000</SVIZ>
    <BSP>53,830000</BSP>
    <MALT>53,830000</MALT>
    <XAUS>53,830000</XAUS>
    <XFRA>53,830000</XFRA>
  </Prezzi>
  <Prezzi>
    <Data>20181217</Data>
    <Mercato>MGP</Mercato>
    <Ora>5</Ora>
    <PUN>54,250000</PUN>
    <NAT>54,250000</NAT>
    <CNOR>54,250000</CNOR>
    <CSUD>54,250000</CSUD>
    <NORD>54,250000</NORD>
    <SARD>54,250000</SARD>
    <SICI>54,250000</SICI>
    <SUD>54,250000</SUD>
    <AUST>54,250000</AUST>
    <BRNN>54,250000</BRNN>
    <COAC>54,250000</COAC>
    <CORS>54,250000</CORS>
    <FOGN>54,250000</FOGN>
    <FRAN>54,250000</FRAN>
    <GREC>54,250000</GREC>
    <MFTV>54,250000</MFTV>
    <PRGP>54,250000</PRGP>
    <ROSN>54,250000</ROSN>
    <SLOV>54,250000</SLOV>
    <SVIZ>54,250000</SVIZ>
    <BSP>54,250000</BSP>
    <MALT>54,250000</MALT>
    <XAUS>54,250000</XAUS>
    <XFRA>54,250000</XFRA>
  </Prezzi>
  <Prezzi>
    <Data>20181217</Data>
    <Mercato>MGP</Mercato>
    <Ora>6</Ora>
    <PUN>55,880000</PUN>
    <NAT>55,880000</NAT>
    <CNOR>55,880000</CNOR>
    <CSUD>55,880000</CSUD>
    <NORD>55,880000</NORD>
    <SARD>55,880000</SARD>
    <SICI>55,880000</SICI>
    <SUD>55,880000</SUD>
    <AUST>55,880000</AUST>
    <BRNN>55,880000</BRNN>
    <COAC>55,880000</COAC>
    <CORS>55,880000</CORS>
    <FOGN>55,880000</FOGN>
    <FRAN>55,880000</FRAN>
    <GREC>55,880000</GREC>
    <MFTV>55,880000</MFTV>
    <PRGP>55,880000</PRGP>
    <ROSN>55,880000</ROSN>
    <SLOV>55,880000</SLOV>
    <SVIZ>55,880000</SVIZ>
    <BSP>55,880000</BSP>
    <MALT>55,880000</MALT>
    <XAUS>55,880000</XAUS>
    <XFRA>55,880000</XFRA>
  </Prezzi>
  <Prezzi>
    <Data>20181217</Data>
    <Mercato>MGP</Mercato>
    <Ora>7</Ora>
    <PUN>65,032380</PUN>
    <NAT>64,240000</NAT>
    <CNOR>65,150000</CNOR>
    <CSUD>65,150000</CSUD>
    <NORD>65,150000</NORD>
    <SARD>65,150000</SARD>
    <SICI>64,240000</SICI>
    <SUD>64,240000</SUD>
    <AUST>65,150000</AUST>
    <BRNN>64,240000</BRNN>
    <COAC>65,150000</COAC>
    <CORS>65,150000</CORS>
    <FOGN>64,240000</FOGN>
    <FRAN>65,150000</FRAN>
    <GREC>64,240000</GREC>
    <MFTV>65,150000</MFTV>
    <PRGP>64,240000</PRGP>
    <ROSN>64,240000</ROSN>
    <SLOV>65,150000</SLOV>
    <SVIZ>65,150000</SVIZ>
    <BSP>65,150000</BSP>
    <MALT>64,240000</MALT>
    <XAUS>65,150000</XAUS>
    <XFRA>65,150000</XFRA>
  </Prezzi>
  <Prezzi>
    <Data>20181217</Data>
    <Mercato>MGP</Mercato>
    <Ora>8</Ora>
    <PUN>76,370130</PUN>
    <NAT>73,000000</NAT>
    <CNOR>78,097180</CNOR>
    <CSUD>78,097180</CSUD>
    <NORD>78,097180</NORD>
    <SARD>78,097180</SARD>
    <SICI>64,370000</SICI>
    <SUD>64,370000</SUD>
    <AUST>78,097180</AUST>
    <BRNN>64,370000</BRNN>
    <COAC>78,097180</COAC>
    <CORS>78,097180</CORS>
    <FOGN>64,370000</FOGN>
    <FRAN>78,097180</FRAN>
    <GREC>64,370000</GREC>
    <MFTV>78,097180</MFTV>
    <PRGP>64,370000</PRGP>
    <ROSN>64,370000</ROSN>
    <SLOV>78,097180</SLOV>
    <SVIZ>78,097180</SVIZ>
    <BSP>78,097180</BSP>
    <MALT>64,370000</MALT>
    <XAUS>78,097180</XAUS>
    <XFRA>78,097180</XFRA>
  </Prezzi>
  <Prezzi>
    <Data>20181217</Data>
    <Mercato>MGP</Mercato>
    <Ora>9</Ora>
    <PUN>81,265310</PUN>
    <NAT>75,960000</NAT>
    <CNOR>83,699470</CNOR>
    <CSUD>83,699470</CSUD>
    <NORD>83,699470</NORD>
    <SARD>83,699470</SARD>
    <SICI>64,240000</SICI>
    <SUD>64,240000</SUD>
    <AUST>83,699470</AUST>
    <BRNN>64,240000</BRNN>
    <COAC>83,699470</COAC>
    <CORS>83,699470</CORS>
    <FOGN>64,240000</FOGN>
    <FRAN>83,699470</FRAN>
    <GREC>64,240000</GREC>
    <MFTV>83,699470</MFTV>
    <PRGP>64,240000</PRGP>
    <ROSN>64,240000</ROSN>
    <SLOV>83,699470</SLOV>
    <SVIZ>83,699470</SVIZ>
    <BSP>83,699470</BSP>
    <MALT>64,240000</MALT>
    <XAUS>83,699470</XAUS>
    <XFRA>83,699470</XFRA>
  </Prezzi>
  <Prezzi>
    <Data>20181217</Data>
    <Mercato>MGP</Mercato>
    <Ora>10</Ora>
    <PUN>86,720380</PUN>
    <NAT>75,060000</NAT>
    <CNOR>90,010000</CNOR>
    <CSUD>90,010000</CSUD>
    <NORD>90,010000</NORD>
    <SARD>90,010000</SARD>
    <SICI>63,240000</SICI>
    <SUD>63,240000</SUD>
    <AUST>90,010000</AUST>
    <BRNN>63,240000</BRNN>
    <COAC>90,010000</COAC>
    <CORS>90,010000</CORS>
    <FOGN>63,240000</FOGN>
    <FRAN>90,010000</FRAN>
    <GREC>63,240000</GREC>
    <MFTV>90,010000</MFTV>
    <PRGP>63,240000</PRGP>
    <ROSN>63,240000</ROSN>
    <SLOV>90,010000</SLOV>
    <SVIZ>90,010000</SVIZ>
    <BSP>90,010000</BSP>
    <MALT>63,240000</MALT>
    <XAUS>90,010000</XAUS>
    <XFRA>90,010000</XFRA>
  </Prezzi>
  <Prezzi>
    <Data>20181217</Data>
    <Mercato>MGP</Mercato>
    <Ora>11</Ora>
    <PUN>86,652200</PUN>
    <NAT>73,510000</NAT>
    <CNOR>90,000000</CNOR>
    <CSUD>90,000000</CSUD>
    <NORD>90,000000</NORD>
    <SARD>90,000000</SARD>
    <SICI>62,260000</SICI>
    <SUD>62,260000</SUD>
    <AUST>90,000000</AUST>
    <BRNN>62,260000</BRNN>
    <COAC>90,000000</COAC>
    <CORS>90,000000</CORS>
    <FOGN>62,260000</FOGN>
    <FRAN>90,000000</FRAN>
    <GREC>62,260000</GREC>
    <MFTV>90,000000</MFTV>
    <PRGP>62,260000</PRGP>
    <ROSN>62,260000</ROSN>
    <SLOV>90,000000</SLOV>
    <SVIZ>90,000000</SVIZ>
    <BSP>90,000000</BSP>
    <MALT>62,260000</MALT>
    <XAUS>90,000000</XAUS>
    <XFRA>90,000000</XFRA>
  </Prezzi>
  <Prezzi>
    <Data>20181217</Data>
    <Mercato>MGP</Mercato>
    <Ora>12</Ora>
    <PUN>86,730240</PUN>
    <NAT>72,120000</NAT>
    <CNOR>90,070000</CNOR>
    <CSUD>90,070000</CSUD>
    <NORD>90,070000</NORD>
    <SARD>90,070000</SARD>
    <SICI>62,260000</SICI>
    <SUD>62,260000</SUD>
    <AUST>90,070000</AUST>
    <BRNN>62,260000</BRNN>
    <COAC>90,070000</COAC>
    <CORS>90,070000</CORS>
    <FOGN>62,260000</FOGN>
    <FRAN>90,070000</FRAN>
    <GREC>62,260000</GREC>
    <MFTV>90,070000</MFTV>
    <PRGP>62,260000</PRGP>
    <ROSN>62,260000</ROSN>
    <SLOV>90,070000</SLOV>
    <SVIZ>90,070000</SVIZ>
    <BSP>90,070000</BSP>
    <MALT>62,260000</MALT>
    <XAUS>90,070000</XAUS>
    <XFRA>90,070000</XFRA>
  </Prezzi>
  <Prezzi>
    <Data>20181217</Data>
    <Mercato>MGP</Mercato>
    <Ora>13</Ora>
    <PUN>76,602080</PUN>
    <NAT>69,340000</NAT>
    <CNOR>79,018810</CNOR>
    <CSUD>79,018810</CSUD>
    <NORD>79,018810</NORD>
    <SARD>79,018810</SARD>
    <SICI>60,000000</SICI>
    <SUD>60,000000</SUD>
    <AUST>79,018810</AUST>
    <BRNN>60,000000</BRNN>
    <COAC>79,018810</COAC>
    <CORS>79,018810</CORS>
    <FOGN>60,000000</FOGN>
    <FRAN>79,018810</FRAN>
    <GREC>60,000000</GREC>
    <MFTV>79,018810</MFTV>
    <PRGP>60,000000</PRGP>
    <ROSN>60,000000</ROSN>
    <SLOV>79,018810</SLOV>
    <SVIZ>79,018810</SVIZ>
    <BSP>79,018810</BSP>
    <MALT>60,000000</MALT>
    <XAUS>79,018810</XAUS>
    <XFRA>79,018810</XFRA>
  </Prezzi>
  <Prezzi>
    <Data>20181217</Data>
    <Mercato>MGP</Mercato>
    <Ora>14</Ora>
    <PUN>76,614190</PUN>
    <NAT>69,100000</NAT>
    <CNOR>79,013550</CNOR>
    <CSUD>79,013550</CSUD>
    <NORD>79,013550</NORD>
    <SARD>79,013550</SARD>
    <SICI>60,000000</SICI>
    <SUD>60,000000</SUD>
    <AUST>79,013550</AUST>
    <BRNN>60,000000</BRNN>
    <COAC>79,013550</COAC>
    <CORS>79,013550</CORS>
    <FOGN>60,000000</FOGN>
    <FRAN>79,013550</FRAN>
    <GREC>60,000000</GREC>
    <MFTV>79,013550</MFTV>
    <PRGP>60,000000</PRGP>
    <ROSN>60,000000</ROSN>
    <SLOV>79,013550</SLOV>
    <SVIZ>79,013550</SVIZ>
    <BSP>79,013550</BSP>
    <MALT>60,000000</MALT>
    <XAUS>79,013550</XAUS>
    <XFRA>79,013550</XFRA>
  </Prezzi>
  <Prezzi>
    <Data>20181217</Data>
    <Mercato>MGP</Mercato>
    <Ora>15</Ora>
    <PUN>76,950440</PUN>
    <NAT>69,280000</NAT>
    <CNOR>79,033280</CNOR>
    <CSUD>79,033280</CSUD>
    <NORD>79,033280</NORD>
    <SARD>79,033280</SARD>
    <SICI>62,260000</SICI>
    <SUD>62,260000</SUD>
    <AUST>79,033280</AUST>
    <BRNN>62,260000</BRNN>
    <COAC>79,033280</COAC>
    <CORS>79,033280</CORS>
    <FOGN>62,260000</FOGN>
    <FRAN>79,033280</FRAN>
    <GREC>62,260000</GREC>
    <MFTV>79,033280</MFTV>
    <PRGP>62,260000</PRGP>
    <ROSN>62,260000</ROSN>
    <SLOV>79,033280</SLOV>
    <SVIZ>79,033280</SVIZ>
    <BSP>79,033280</BSP>
    <MALT>62,260000</MALT>
    <XAUS>79,033280</XAUS>
    <XFRA>79,033280</XFRA>
  </Prezzi>
  <Prezzi>
    <Data>20181217</Data>
    <Mercato>MGP</Mercato>
    <Ora>16</Ora>
    <PUN>86,514490</PUN>
    <NAT>73,310000</NAT>
    <CNOR>90,010000</CNOR>
    <CSUD>90,010000</CSUD>
    <NORD>90,010000</NORD>
    <SARD>90,010000</SARD>
    <SICI>62,260000</SICI>
    <SUD>62,260000</SUD>
    <AUST>90,010000</AUST>
    <BRNN>62,260000</BRNN>
    <COAC>90,010000</COAC>
    <CORS>90,010000</CORS>
    <FOGN>62,260000</FOGN>
    <FRAN>90,010000</FRAN>
    <GREC>62,260000</GREC>
    <MFTV>90,010000</MFTV>
    <PRGP>62,260000</PRGP>
    <ROSN>62,260000</ROSN>
    <SLOV>90,010000</SLOV>
    <SVIZ>90,010000</SVIZ>
    <BSP>90,010000</BSP>
    <MALT>62,260000</MALT>
    <XAUS>90,010000</XAUS>
    <XFRA>90,010000</XFRA>
  </Prezzi>
  <Prezzi>
    <Data>20181217</Data>
    <Mercato>MGP</Mercato>
    <Ora>17</Ora>
    <PUN>90,825770</PUN>
    <NAT>77,990000</NAT>
    <CNOR>95,000000</CNOR>
    <CSUD>95,000000</CSUD>
    <NORD>95,000000</NORD>
    <SARD>95,000000</SARD>
    <SICI>63,240000</SICI>
    <SUD>63,240000</SUD>
    <AUST>95,000000</AUST>
    <BRNN>63,240000</BRNN>
    <COAC>95,000000</COAC>
    <CORS>95,000000</CORS>
    <FOGN>63,240000</FOGN>
    <FRAN>95,000000</FRAN>
    <GREC>63,240000</GREC>
    <MFTV>95,000000</MFTV>
    <PRGP>63,240000</PRGP>
    <ROSN>63,240000</ROSN>
    <SLOV>95,000000</SLOV>
    <SVIZ>95,000000</SVIZ>
    <BSP>95,000000</BSP>
    <MALT>63,240000</MALT>
    <XAUS>95,000000</XAUS>
    <XFRA>95,000000</XFRA>
  </Prezzi>
  <Prezzi>
    <Data>20181217</Data>
    <Mercato>MGP</Mercato>
    <Ora>18</Ora>
    <PUN>93,138780</PUN>
    <NAT>87,390000</NAT>
    <CNOR>96,660000</CNOR>
    <CSUD>96,660000</CSUD>
    <NORD>96,660000</NORD>
    <SARD>96,660000</SARD>
    <SICI>81,000000</SICI>
    <SUD>64,240000</SUD>
    <AUST>96,660000</AUST>
    <BRNN>64,240000</BRNN>
    <COAC>96,660000</COAC>
    <CORS>96,660000</CORS>
    <FOGN>64,240000</FOGN>
    <FRAN>96,660000</FRAN>
    <GREC>64,240000</GREC>
    <MFTV>96,660000</MFTV>
    <PRGP>81,000000</PRGP>
    <ROSN>64,240000</ROSN>
    <SLOV>96,660000</SLOV>
    <SVIZ>96,660000</SVIZ>
    <BSP>96,660000</BSP>
    <MALT>81,000000</MALT>
    <XAUS>96,660000</XAUS>
    <XFRA>96,660000</XFRA>
  </Prezzi>
  <Prezzi>
    <Data>20181217</Data>
    <Mercato>MGP</Mercato>
    <Ora>19</Ora>
    <PUN>87,361900</PUN>
    <NAT>76,780000</NAT>
    <CNOR>90,000000</CNOR>
    <CSUD>90,000000</CSUD>
    <NORD>90,000000</NORD>
    <SARD>90,000000</SARD>
    <SICI>81,000000</SICI>
    <SUD>64,240000</SUD>
    <AUST>90,000000</AUST>
    <BRNN>64,240000</BRNN>
    <COAC>90,000000</COAC>
    <CORS>90,000000</CORS>
    <FOGN>64,240000</FOGN>
    <FRAN>90,000000</FRAN>
    <GREC>64,240000</GREC>
    <MFTV>90,000000</MFTV>
    <PRGP>81,000000</PRGP>
    <ROSN>64,240000</ROSN>
    <SLOV>90,000000</SLOV>
    <SVIZ>90,000000</SVIZ>
    <BSP>90,000000</BSP>
    <MALT>81,000000</MALT>
    <XAUS>90,000000</XAUS>
    <XFRA>90,000000</XFRA>
  </Prezzi>
  <Prezzi>
    <Data>20181217</Data>
    <Mercato>MGP</Mercato>
    <Ora>20</Ora>
    <PUN>77,901220</PUN>
    <NAT>73,490000</NAT>
    <CNOR>79,000000</CNOR>
    <CSUD>79,000000</CSUD>
    <NORD>79,000000</NORD>
    <SARD>79,000000</SARD>
    <SICI>81,000000</SICI>
    <SUD>64,240000</SUD>
    <AUST>79,000000</AUST>
    <BRNN>64,240000</BRNN>
    <COAC>79,000000</COAC>
    <CORS>79,000000</CORS>
    <FOGN>64,240000</FOGN>
    <FRAN>79,000000</FRAN>
    <GREC>64,240000</GREC>
    <MFTV>79,000000</MFTV>
    <PRGP>81,000000</PRGP>
    <ROSN>64,240000</ROSN>
    <SLOV>79,000000</SLOV>
    <SVIZ>79,000000</SVIZ>
    <BSP>79,000000</BSP>
    <MALT>81,000000</MALT>
    <XAUS>79,000000</XAUS>
    <XFRA>79,000000</XFRA>
  </Prezzi>
  <Prezzi>
    <Data>20181217</Data>
    <Mercato>MGP</Mercato>
    <Ora>21</Ora>
    <PUN>74,429380</PUN>
    <NAT>69,510000</NAT>
    <CNOR>75,035730</CNOR>
    <CSUD>75,035730</CSUD>
    <NORD>75,035730</NORD>
    <SARD>75,035730</SARD>
    <SICI>81,000000</SICI>
    <SUD>63,260000</SUD>
    <AUST>75,035730</AUST>
    <BRNN>63,260000</BRNN>
    <COAC>75,035730</COAC>
    <CORS>75,035730</CORS>
    <FOGN>63,260000</FOGN>
    <FRAN>75,035730</FRAN>
    <GREC>63,260000</GREC>
    <MFTV>75,035730</MFTV>
    <PRGP>81,000000</PRGP>
    <ROSN>63,260000</ROSN>
    <SLOV>75,035730</SLOV>
    <SVIZ>75,035730</SVIZ>
    <BSP>75,035730</BSP>
    <MALT>81,000000</MALT>
    <XAUS>75,035730</XAUS>
    <XFRA>75,035730</XFRA>
  </Prezzi>
  <Prezzi>
    <Data>20181217</Data>
    <Mercato>MGP</Mercato>
    <Ora>22</Ora>
    <PUN>66,893970</PUN>
    <NAT>64,370000</NAT>
    <CNOR>68,150000</CNOR>
    <CSUD>68,150000</CSUD>
    <NORD>68,150000</NORD>
    <SARD>68,150000</SARD>
    <SICI>59,700000</SICI>
    <SUD>59,700000</SUD>
    <AUST>68,150000</AUST>
    <BRNN>59,700000</BRNN>
    <COAC>68,150000</COAC>
    <CORS>68,150000</CORS>
    <FOGN>59,700000</FOGN>
    <FRAN>68,150000</FRAN>
    <GREC>59,700000</GREC>
    <MFTV>68,150000</MFTV>
    <PRGP>59,700000</PRGP>
    <ROSN>59,700000</ROSN>
    <SLOV>68,150000</SLOV>
    <SVIZ>68,150000</SVIZ>
    <BSP>68,150000</BSP>
    <MALT>59,700000</MALT>
    <XAUS>68,150000</XAUS>
    <XFRA>68,150000</XFRA>
  </Prezzi>
  <Prezzi>
    <Data>20181217</Data>
    <Mercato>MGP</Mercato>
    <Ora>23</Ora>
    <PUN>63,571670</PUN>
    <NAT>63,260000</NAT>
    <CNOR>64,800000</CNOR>
    <CSUD>64,800000</CSUD>
    <NORD>64,800000</NORD>
    <SARD>64,800000</SARD>
    <SICI>56,500000</SICI>
    <SUD>56,500000</SUD>
    <AUST>64,800000</AUST>
    <BRNN>56,500000</BRNN>
    <COAC>64,800000</COAC>
    <CORS>64,800000</CORS>
    <FOGN>56,500000</FOGN>
    <FRAN>64,800000</FRAN>
    <GREC>56,500000</GREC>
    <MFTV>64,800000</MFTV>
    <PRGP>56,500000</PRGP>
    <ROSN>56,500000</ROSN>
    <SLOV>64,800000</SLOV>
    <SVIZ>64,800000</SVIZ>
    <BSP>64,800000</BSP>
    <MALT>56,500000</MALT>
    <XAUS>64,800000</XAUS>
    <XFRA>64,800000</XFRA>
  </Prezzi>
  <Prezzi>
    <Data>20181217</Data>
    <Mercato>MGP</Mercato>
    <Ora>24</Ora>
    <PUN>59,130390</PUN>
    <NAT>58,820000</NAT>
    <CNOR>59,950000</CNOR>
    <CSUD>59,950000</CSUD>
    <NORD>59,950000</NORD>
    <SARD>59,950000</SARD>
    <SICI>54,250000</SICI>
    <SUD>54,250000</SUD>
    <AUST>59,950000</AUST>
    <BRNN>54,250000</BRNN>
    <COAC>59,950000</COAC>
    <CORS>59,950000</CORS>
    <FOGN>54,250000</FOGN>
    <FRAN>59,950000</FRAN>
    <GREC>54,250000</GREC>
    <MFTV>59,950000</MFTV>
    <PRGP>54,250000</PRGP>
    <ROSN>54,250000</ROSN>
    <SLOV>59,950000</SLOV>
    <SVIZ>59,950000</SVIZ>
    <BSP>59,950000</BSP>
    <MALT>54,250000</MALT>
    <XAUS>59,950000</XAUS>
    <XFRA>59,950000</XFRA>
  </Prezzi>
</NewDataSet>